awsssomanager/__init__.py
awsssomanager/cli/__init__.py
awsssomanager/cli/cli.py
awsssomanager/config/__init__.py
awsssomanager/config/config.py
awsssomanager/config/schema.yml
awsssomanager/constants.py
awsssomanager/sso/__init__.py
awsssomanager/sso/credentials.py
awsssomanager/sso/device.py
awsssomanager/sso/roles.py
awsssomanager/sso/token.py
awsssomanager/utils/__init__.py
awsssomanager/utils/general.py
awsssomanager/utils/validators.py
awsssomanager-0.3.0.dist-info/LICENSE
awsssomanager-0.3.0.dist-info/METADATA
awsssomanager-0.3.0.dist-info/WHEEL
awsssomanager-0.3.0.dist-info/entry_points.txt
awsssomanager-0.3.0.dist-info/RECORD
