Metadata-Version: 2.1
Name: awsssomanager
Version: 0.3.0
Summary: AWS SSO Manager
License: MIT
Author: Brett Fitzpatrick
Requires-Python: >=3.9,<4.0
Classifier: License :: OSI Approved :: MIT License
Classifier: Programming Language :: Python :: 3
Classifier: Programming Language :: Python :: 3.9
Classifier: Programming Language :: Python :: 3.10
Classifier: Programming Language :: Python :: 3.11
Classifier: Programming Language :: Python :: 3.12
Requires-Dist: boto3 (>=1.35.24,<2.0.0)
Requires-Dist: click (>=8.1.7,<9.0.0)
Requires-Dist: coloredlogs (>=15.0.1,<16.0.0)
Requires-Dist: pyyaml (>=6.0.2,<7.0.0)
Requires-Dist: yamale (>=5.2.1,<6.0.0)
